perimod/__init__.py
perimod-1.0.1.dist-info/LICENSE.txt
perimod-1.0.1.dist-info/WHEEL
perimod-1.0.1.dist-info/METADATA
perimod-1.0.1.dist-info/RECORD
