Metadata-Version: 2.1
Name: perimod
Version: 1.0.1
Summary: Peridot module maker in Python
License: BSD-3-Clause
Author: Totobird
Requires-Python: >=3.8,<4.0
Classifier: License :: OSI Approved :: BSD License
Classifier: Programming Language :: Python :: 3
Classifier: Programming Language :: Python :: 3.8
